clowclow/__init__.py
clowclow/claude_client.py
clowclow/claude_code_model.py
clowclow/constants.py
clowclow/dynamic_model_builder.py
clowclow/multimodal_handler.py
clowclow/py.typed
clowclow/query_strategies.py
clowclow/request_handler.py
clowclow-0.2.0.dist-info/WHEEL
clowclow-0.2.0.dist-info/entry_points.txt
clowclow-0.2.0.dist-info/METADATA
clowclow-0.2.0.dist-info/RECORD
