Metadata-Version: 2.3
Name: clowclow
Version: 0.2.0
Summary: Make Claude Code available to Pydantic AI
Requires-Dist: claude-agent-sdk>=0.1.0
Requires-Dist: pydantic-ai>=1.0.5
Requires-Python: >=3.13
Project-URL: Bug Reports, https://github.com/huscarldev/clowclow/issues
Project-URL: Documentation, https://github.com/huscarldev/clowclow#readme
Project-URL: Repository, https://github.com/huscarldev/clowclow
Project-URL: Source Code, https://github.com/huscarldev/clowclow
